crun/__init__.py
crun/crun.py
cpp_runner-0.1.0.dist-info/METADATA
cpp_runner-0.1.0.dist-info/WHEEL
cpp_runner-0.1.0.dist-info/entry_points.txt
cpp_runner-0.1.0.dist-info/top_level.txt
cpp_runner-0.1.0.dist-info/RECORD
