Metadata-Version: 2.1
Name: cpp-runner
Version: 0.1.0
Summary: A simple, small command line utility to run cpp files.
Home-page: https://github.com/macaquedev/cpp-runner
Author: Alex Pylypenko
Author-email: macaquedev@gmail.com
License: MIT
Requires-Python: >=3.3
Requires-Dist: setuptools
Requires-Dist: pip
